tema_ai/__init__.py
tema_ai/connect/__init__.py
tema_ai/connect/casting.py
tema_ai/connect/constants.py
tema_ai/connect/credentials.py
tema_ai/connect/delta_sharing/__init__.py
tema_ai/connect/delta_sharing/json_predicate_hints.py
tema_ai/connect/delta_sharing/patch.py
tema_ai/connect/delta_sharing/tests/__init__.py
tema_ai/connect/delta_sharing/tests/test_patch.py
tema_ai/connect/delta_sharing/tests/test_utils.py
tema_ai/connect/delta_sharing/utils.py
tema_ai/connect/protocol.py
tema_ai/connect/sharing.py
tema_ai/connect/tests/__init__.py
tema_ai/connect/tests/test_credentials.py
tema_ai/connect/tests/test_protocol.py
tema_ai/connect/tests/test_sharing.py
tema_ai/connect/tests/test_tokens.py
tema_ai/connect/tests/test_utils.py
tema_ai/connect/tokens.py
tema_ai/connect/types.py
tema_ai/connect/utils.py
tema_ai-0.17.0.dist-info/LICENSE
tema_ai-0.17.0.dist-info/METADATA
tema_ai-0.17.0.dist-info/WHEEL
tema_ai-0.17.0.dist-info/RECORD
