Metadata-Version: 2.3
Name: tema-ai
Version: 0.17.0
Summary: A connector to the Tema AI APIs
Author: Tema AI - Engineering
Author-email: engineering@tema.ai
Requires-Python: >=3.8,<3.13
Classifier: Programming Language :: Python :: 3
Classifier: Programming Language :: Python :: 3.8
Classifier: Programming Language :: Python :: 3.9
Classifier: Programming Language :: Python :: 3.10
Classifier: Programming Language :: Python :: 3.11
Classifier: Programming Language :: Python :: 3.12
Provides-Extra: dev
Requires-Dist: delta-sharing (>=1.3.2,<2.0.0)
Requires-Dist: freezegun (>=1.2.2,<2.0.0) ; extra == "dev"
Requires-Dist: mypy (>=1.3.0,<2.0.0) ; extra == "dev"
Requires-Dist: pandas (>=1.3.3,<3.0.0)
Requires-Dist: parameterized (>=0.9.0,<0.10.0) ; extra == "dev"
Requires-Dist: pyarrow (>=6.0.0)
Requires-Dist: python-dotenv (>=0.10.0,<3.0.0)
Requires-Dist: requests (>=2.32.0,<3.0.0)
